chemesis3.i
setup.py
chemesis3/__cbi__.py
chemesis3/__init__.py
chemesis3/chemesis3_base.py
chemesis3/components.py
chemesis3.egg-info/PKG-INFO
chemesis3.egg-info/SOURCES.txt
chemesis3.egg-info/dependency_links.txt
chemesis3.egg-info/top_level.txt