Metadata-Version: 1.0
Name: chemesis3
Version: 0.0.0-alpha
Summary: Kinetic reaction and biochemical reaction pathways for G-3.
Home-page: http://genesis-sim.org
Author: Mando Rodriguez
Author-email: rodrigueza14@uthscsa.edu
License: GPL
Keywords: neuroscience neurosimulator simulator modeling GENESIS
Platform: Unix
Platform: Lunix
Platform: MacOS X
Classifier: Development Status :: 3 - Alpha
Classifier: Environment :: Console
Classifier: Intended Audience :: End Users/Desktop
Classifier: Intended Audience :: Developers
Classifier: Intended Audience :: Science/Research
Classifier: License :: OSI Approved :: GNU General Public License (GPL)
Classifier: Operating System :: MacOS :: MacOS X
Classifier: Operating System :: POSIX :: Linux
Classifier: Programming Language :: Python :: 2.5
Classifier: Programming Language :: Python :: 2.6
Classifier: Topic :: Software Development :: Libraries :: Python Modules
